envy/__init__.py
envy/crypto.py
envy/main.py
envy/storage.py
envy/utils.py
envy_secrets-0.1.1.dist-info/METADATA
envy_secrets-0.1.1.dist-info/WHEEL
envy_secrets-0.1.1.dist-info/entry_points.txt
envy_secrets-0.1.1.dist-info/licenses/LICENSE
envy_secrets-0.1.1.dist-info/RECORD
