Metadata-Version: 2.4
Name: envy-secrets
Version: 0.1.1
Summary: Git for your .env files - Secure environment variable management with encryption
Project-URL: Homepage, https://github.com/KRISHNA-JAIN15/ENVY
Project-URL: Documentation, https://github.com/KRISHNA-JAIN15/ENVY#readme
Project-URL: Repository, https://github.com/KRISHNA-JAIN15/ENVY
Project-URL: Issues, https://github.com/KRISHNA-JAIN15/ENVY/issues
Author-email: Krishna Jain <krishnajain1502@gmail.com>
License-Expression: MIT
License-File: LICENSE
Keywords: cli,devops,dotenv,encryption,env,environment,secrets,security
Classifier: Development Status :: 4 - Beta
Classifier: Environment :: Console
Classifier: Intended Audience :: Developers
Classifier: License :: OSI Approved :: MIT License
Classifier: Operating System :: OS Independent
Classifier: Programming Language :: Python :: 3
Classifier: Programming Language :: Python :: 3.10
Classifier: Programming Language :: Python :: 3.11
Classifier: Programming Language :: Python :: 3.12
Classifier: Topic :: Security
Classifier: Topic :: Software Development :: Libraries :: Python Modules
Classifier: Topic :: Utilities
Requires-Python: >=3.10
Requires-Dist: cryptography<43.0.0,>=41.0.0
Requires-Dist: keyring<26.0.0,>=24.0.0
Requires-Dist: pyyaml<7.0.0,>=6.0.0
Requires-Dist: requests<3.0.0,>=2.28.0
Requires-Dist: rich<14.0.0,>=13.0.0
Requires-Dist: typer[all]<1.0.0,>=0.9.0
Provides-Extra: dev
Requires-Dist: black>=23.0.0; extra == 'dev'
Requires-Dist: pytest-cov>=4.0.0; extra == 'dev'
Requires-Dist: pytest>=7.0.0; extra == 'dev'
Requires-Dist: ruff>=0.1.0; extra == 'dev'
